setup.py
datemike/__init__.py
datemike/ansible.py
datemike/base.py
datemike/utils.py
datemike.egg-info/PKG-INFO
datemike.egg-info/SOURCES.txt
datemike.egg-info/dependency_links.txt
datemike.egg-info/requires.txt
datemike.egg-info/top_level.txt