Metadata-Version: 1.0
Name: datemike
Version: 0.1.1
Summary: Create Ansible tasks, plays, and playbooks in pure Python
Home-page: https://github.com/angstwad/datemike
Author: Paul Durivage
Author-email: pauldurivage@gmail.com
License: Apache v2.0
Platform: UNKNOWN
